Metadata-Version: 1.1
Name: bibsubset
Version: 0.0.1
Summary: Extract bibtex subset
Home-page: https://hydra.ecd.space/eduard/bibsubset/
Author: Eduard Christian Dumitrescu
Author-email: UNKNOWN
License: LGPLv3
Platform: UNKNOWN
Classifier: Programming Language :: Python :: 3 :: Only
